{
	"pages": [ //pages数组中第一项表示应用启动页，参考：https://uniapp.dcloud.io/collocation/pages
		{
			"path": "pages/workbenches/index",
			"style": {
				"navigationBarTitleText": "卫生员",
				"navigationStyle": "custom"
			}
		},
		{
			"path": "pages/house/index",
			"style": {
				"navigationBarTitleText": "卫生员",
				"navigationStyle": "custom"
			}
		},
		{
			"path": "pages/msg/index",
			"style": {
				"navigationBarTitleText": "消息"
			}
		},
		{
			"path": "pages/user/index",
			"style": {
				"navigationBarTitleText": "我的",
				"navigationStyle": "custom"
			}
		},
		{
			"path": "pages/workbenches/waitClean",
			"style": {
				"navigationBarTitleText": "待打扫房屋"
			}
		},
		{
			"path": "pages/workbenches/ecoDetail",
			"style": {
				"navigationBarTitleText": "",
				"navigationStyle": "custom"
			}
		},
		{
			"path": "pages/workbenches/subEco",
			"style": {
				"navigationBarTitleText": "打扫完成"
			}
		},
		{
			"path": "pages/workbenches/ecoInfo",
			"style": {
				"navigationBarTitleText": "打扫详情"
			}
		},
		{
			"path": "pages/user/ecoLogList",
			"style": {
				"navigationBarTitleText": "",
				"navigationStyle": "custom"
			}
		},
		{
			"path": "pages/trusteeship/index",
			"style": {
				"navigationBarTitleText": "我想托管"
			}
		},
		{
			"path": "pages/trusteeship/success",
			"style": {
				"navigationBarTitleText": "申请成功"
			}
		}
	],
	"globalStyle": {
		"navigationBarTextStyle": "black",
		"navigationBarTitleText": "卫生员",
		"navigationBarBackgroundColor": "#F8F8F8",
		"backgroundColor": "#F7F7F7"
	},
	"tabBar": {
		"backgroundColor": "#F7F7F7",
		"borderStyle": "black",
		"color": "#808080",
		"selectedColor": "#1677FF",
		"list": [
			{
				"pagePath": "pages/workbenches/index",
				"iconPath": "static/tabbar1.png",
				"selectedIconPath": "static/tabbar1_active.png",
				"text": "工作台"
			},
			{
				"pagePath": "pages/msg/index",
				"iconPath": "static/tabbar2.png",
				"selectedIconPath": "static/tabbar2_active.png",
				"text": "消息"
			},
			{
				"pagePath": "pages/user/index",
				"iconPath": "static/tabbar3.png",
				"selectedIconPath": "static/tabbar3_active.png",
				"text": "我的"
			}
		]
	},
	"uniIdRouter": {}
}
